pyslite/__init__.py
pyslite/client.py
pyslite/utils/__init__.py
pyslite/utils/note.py
pyslite/utils/notes_response.py
pyslite/utils/tile.py
pyslite-0.0.10.dist-info/LICENSE
pyslite-0.0.10.dist-info/METADATA
pyslite-0.0.10.dist-info/WHEEL
pyslite-0.0.10.dist-info/top_level.txt
pyslite-0.0.10.dist-info/RECORD
