Metadata-Version: 2.2
Name: pyslite
Version: 0.0.10
Summary: Python SDK for interacting with Slite API
Home-page: https://github.com/oddaspa/pyslite
Author: Odd Gunnar Aspaas
Author-email: odd.gunnar.aspaas@gmail.com
Project-URL: Bug Tracker, https://github.com/oddaspa/pyslite/issues
Classifier: Programming Language :: Python :: 3
Classifier: License :: OSI Approved :: MIT License
Classifier: Operating System :: OS Independent
Requires-Python: >=3.9
License-File: LICENSE
Requires-Dist: requests
Requires-Dist: pydantic~=2.0
